malclient/__init__.py
malclient/anime.py
malclient/boards.py
malclient/client.py
malclient/exceptions.py
malclient/manga.py
malclient/my_list.py
malclient/request_handler.py
malclient/Datamodels/__init__.py
malclient/Datamodels/enums.py
malclient/Datamodels/fields.py
malclient/Datamodels/models.py
malclient/Datamodels/pagination.py
malclient_upgraded-1.3.3.dist-info/LICENSE
malclient_upgraded-1.3.3.dist-info/METADATA
malclient_upgraded-1.3.3.dist-info/WHEEL
malclient_upgraded-1.3.3.dist-info/top_level.txt
malclient_upgraded-1.3.3.dist-info/RECORD
