Metadata-Version: 2.1
Name: malclient-upgraded
Version: 1.3.3
Summary: Modified and rewritten using modern models version of James Fotherby malclient
Home-page: https://github.com/ModerNews/MAL-API-Client-Upgraded
Author: ModerNews
Author-email: polski.gruzin.biz@gmail.com
License: UNKNOWN
Project-URL: Documentation, https://mal-api-client-upgraded.readthedocs.io
Platform: UNKNOWN
Classifier: Programming Language :: Python :: 3.9
Classifier: License :: OSI Approved :: MIT License
Classifier: Operating System :: OS Independent
License-File: LICENSE
Requires-Dist: requests
Requires-Dist: pydantic
